<SceneText>
  <FriendlyName>Chapter 4 (Asbel) - End</FriendlyName>
  <Speakers>
    <Section>Speaker</Section>
    <Entry>
      <PointerOffset/>
      <JapaneseText>アスベル</JapaneseText>
      <EnglishText>Asbel</EnglishText>
      <Notes/>
      <Id>28</Id>
      <Status>Done</Status>
    </Entry>
    <Entry>
      <PointerOffset/>
      <JapaneseText>セネル</JapaneseText>
      <EnglishText>Senel</EnglishText>
      <Notes/>
      <Id>14</Id>
      <Status>Done</Status>
    </Entry>
    <Entry>
      <PointerOffset/>
      <JapaneseText>クロエ</JapaneseText>
      <EnglishText>Chloe</EnglishText>
      <Notes/>
      <Id>15</Id>
      <Status>Done</Status>
    </Entry>
    <Entry>
      <PointerOffset/>
      <JapaneseText>シェリア</JapaneseText>
      <EnglishText>Cheria</EnglishText>
      <Notes/>
      <Id>29</Id>
      <Status>Done</Status>
    </Entry>
  </Speakers>
  <Strings>
    <Section>Main Text</Section>
    <Entry>
      <PointerOffset/>
      <JapaneseText>では、その友人の女性に伝えておいてくれ。
二度とパンを武器にしないように</JapaneseText>
      <EnglishText/>
      <Notes/>
      <SpeakerId>28</SpeakerId>
      <Id>1</Id>
      <Status>To Do</Status>
    </Entry>
    <Entry>
      <PointerOffset/>
      <JapaneseText>一応、言っておく。
だが、あいつが素直に聞くとは思えないぞ</JapaneseText>
      <EnglishText/>
      <Notes/>
      <SpeakerId>14</SpeakerId>
      <Id>2</Id>
      <Status>To Do</Status>
    </Entry>
    <Entry>
      <PointerOffset/>
      <JapaneseText>そもそも私達も被害者なんだ。
彼女と一戦交えようものなら
容赦なくパンで殴られるのだからな</JapaneseText>
      <EnglishText/>
      <Notes/>
      <SpeakerId>15</SpeakerId>
      <Id>3</Id>
      <Status>To Do</Status>
    </Entry>
    <Entry>
      <PointerOffset/>
      <JapaneseText>パンで殴られるなんて
身体よりも心にダメージが残りそうね……</JapaneseText>
      <EnglishText/>
      <Notes/>
      <SpeakerId>29</SpeakerId>
      <Id>4</Id>
      <Status>To Do</Status>
    </Entry>
    <Entry>
      <PointerOffset/>
      <JapaneseText>わかってくれるのか……</JapaneseText>
      <EnglishText/>
      <Notes/>
      <SpeakerId>15</SpeakerId>
      <Id>5</Id>
      <Status>To Do</Status>
    </Entry>
    <Entry>
      <PointerOffset/>
      <JapaneseText>大丈夫だ。
いざとなったら
俺が直接その女性と話し合う</JapaneseText>
      <EnglishText/>
      <Notes/>
      <SpeakerId>28</SpeakerId>
      <Id>6</Id>
      <Status>To Do</Status>
    </Entry>
    <Entry>
      <PointerOffset/>
      <JapaneseText>パンによる秋雨のような
怒濤の突きが飛んでこようとも
俺は一歩も退くつもりはない</JapaneseText>
      <EnglishText/>
      <Notes/>
      <SpeakerId>28</SpeakerId>
      <Id>7</Id>
      <Status>To Do</Status>
    </Entry>
    <Entry>
      <PointerOffset/>
      <JapaneseText>パンの気持ちは、俺が守り抜いてみせる！</JapaneseText>
      <EnglishText/>
      <Notes/>
      <SpeakerId>28</SpeakerId>
      <Id>8</Id>
      <Status>To Do</Status>
    </Entry>
  </Strings>
  <Strings>
    <Section>Unreferenced</Section>
    <Entry>
      <PointerOffset/>
      <JapaneseText>BG06a.ppt</JapaneseText>
      <EnglishText/>
      <Notes/>
      <Id>0</Id>
      <Status>To Do</Status>
    </Entry>
  </Strings>
</SceneText>
