<SceneText>
  <Speakers>
    <Section>Speaker</Section>
    <Entry>
      <PointerOffset/>
      <JapaneseText>System</JapaneseText>
      <EnglishText>System</EnglishText>
      <Notes/>
      <Id>0</Id>
      <Status>Done</Status>
    </Entry>
    <Entry>
      <PointerOffset/>
      <JapaneseText>ミッション開始！</JapaneseText>
      <EnglishText/>
      <Notes/>
      <Id>1</Id>
      <Status>To Do</Status>
    </Entry>
    <Entry>
      <PointerOffset/>
      <JapaneseText>ミッション成功！</JapaneseText>
      <EnglishText/>
      <Notes/>
      <Id>2</Id>
      <Status>To Do</Status>
    </Entry>
    <Entry>
      <PointerOffset/>
      <JapaneseText>ミッション失敗！</JapaneseText>
      <EnglishText/>
      <Notes/>
      <Id>3</Id>
      <Status>To Do</Status>
    </Entry>
  </Speakers>
  <Strings>
    <Section>Scenario</Section>
    <Entry>
      <PointerOffset/>
      <JapaneseText>デュークの闘気が満ちている！</JapaneseText>
      <EnglishText/>
      <Notes/>
      <SpeakerId>0</SpeakerId>
      <Id>0</Id>
      <Status>To Do</Status>
    </Entry>
  </Strings>
  <Strings>
    <Section>Dialog</Section>
    <Entry>
      <PointerOffset/>
      <JapaneseText>８０秒以内に５０Ｋ．Ｏ．を決めろ！\n門を抜けると失敗になるぞ！　注意せよ！</JapaneseText>
      <EnglishText/>
      <Notes/>
      <SpeakerId>1</SpeakerId>
      <Id>1</Id>
      <Status>To Do</Status>
    </Entry>
    <Entry>
      <PointerOffset/>
      <JapaneseText>ボーナス宝箱出現！</JapaneseText>
      <EnglishText/>
      <Notes/>
      <SpeakerId>2</SpeakerId>
      <Id>2</Id>
      <Status>To Do</Status>
    </Entry>
    <Entry>
      <PointerOffset/>
      <JapaneseText>先へ進め！</JapaneseText>
      <EnglishText/>
      <Notes/>
      <SpeakerId>3</SpeakerId>
      <Id>3</Id>
      <Status>To Do</Status>
    </Entry>
  </Strings>
</SceneText>
